{
	"AlphaCutoff" : 0.5,
	"BaseOrDiffuseColor" : 
	[
		1.0,
		1.0,
		1.0
	],
	"DiffuseTransmissionFactor" : 0.0,
	"EmissiveColor" : 
	[
		0.0,
		0.0,
		0.0
	],
	"EmissiveIntensity" : 1.0,
	"EnableAlphaTesting" : false,
	"EnableAsAnalyticLightProxy" : false,
	"EnableBaseTexture" : true,
	"EnableEmissiveTexture" : true,
	"EnableNormalTexture" : true,
	"EnableOcclusionRoughnessMetallicTexture" : true,
	"EnableTransmission" : true,
	"EnableTransmissionTexture" : true,
	"ExcludeFromNEE" : false,
	"IgnoreMeshTangentSpace" : true,
	"IoR" : 1.3999999761581421,
	"Metalness" : 0.0,
	"MetalnessInRedChannel" : false,
	"NestedPriority" : 14,
	"NormalTextureScale" : 0.0,
	"Opacity" : 1.0,
	"PSDDominantDeltaLobe" : 0,
	"PSDExclude" : false,
	"Roughness" : 0.0,
	"ShadowNoLFadeout" : 0.0,
	"SkipRender" : false,
	"SpecularColor" : 
	[
		0.0,
		0.0,
		0.0
	],
	"ThinSurface" : false,
	"TransmissionFactor" : 1.0,
	"UseDonutEmissiveIntensity" : false,
	"UseSpecularGlossModel" : false,
	"VolumeAttenuationColor" : 
	[
		0.5,
		0.80000001192092896,
		1.0
	],
	"VolumeAttenuationDistance" : 0.039999999105930328,
	"version" : 1
}